dexpo/__init__.py
dexpo/__main__.py
dexpo/__version__.py
dexpo/callbacks.py
dexpo/info.py
dexpo/main.py
dexpo/outputs.py
dexpo-0.1.12.dist-info/entry_points.txt
dexpo-0.1.12.dist-info/LICENSE
dexpo-0.1.12.dist-info/METADATA
dexpo-0.1.12.dist-info/WHEEL
dexpo-0.1.12.dist-info/RECORD
