Metadata-Version: 2.1
Name: dexpo
Version: 0.1.12
Summary: Dependency Exposition Boiled Down
Home-page: https://github.com/jackboy2fly/dexpo
License: MIT
Author: Jack Hadaway
Author-email: jack.hadaway@outlook.com
Requires-Python: >=3.11,<4.0
Classifier: License :: OSI Approved :: MIT License
Classifier: Programming Language :: Python :: 3
Classifier: Programming Language :: Python :: 3.11
Classifier: Programming Language :: Python :: 3.12
Requires-Dist: requests (==2.31.0)
Requires-Dist: typer[all] (>=0.9.0,<0.10.0)
Project-URL: Repository, https://github.com/jackboy2fly/dexpo
